
#include "a_code.h"
#include "a_debug.h"


const char* const asC_OpName[NUM_OPCODE] = {

"MOVE",
"LOADK",
"LOADBOOL",
"LOADNIL",
"GETUPVAL",
"GETGLOBAL",
"GETTABLE",
"SETGLOBAL",
"SETUPVAL",
"SETTABLE",
"NEWTABLE",
"SELF",
"ADD",
"SUB",
"MUL",
"DIV",
"MOD",
"POW",
"UNM",
"NOT",
"LEN",
"CONCAT",
"JMP",
"EQ",
"LT",
"LE",
"TEST",
"TESTSET",
"CALL",
"TAILCALL",
"RETURN", 
"FORLOOP",
"FORPREP",
"TFORLOOP",
"SETLIST",
"CLOSE",
"CLOSURE",
"VARARG",
NULL

};



#define OpFormat(t,a,b,c,m) (((t)<<7) | ((a)<<6) | ((b)<<4) | ((c)<<2) | (m))

const as_Byte asC_OpFormat[NUM_OPCODE] = {

/*       T  A  B       C       mode     instruction*/
OpFormat(0, 1, OpArgR, OpArgN, iABC),   /*OP_MOVE*/
OpFormat(0, 1, OpArgK, OpArgN, iABx),   /*OP_LOADK*/
OpFormat(0, 1, OpArgU, OpArgU, iABC),   /*OP_LOADBOOL*/
OpFormat(0, 1, OpArgU, OpArgN, iABC),   /*OP_LOADNIL*/
OpFormat(0, 1, OpArgU, OpArgN, iABC),   /*OP_GETUPVAL*/
OpFormat(0, 1, OpArgK, OpArgN, iABx),   /*OP_GETGLOBAL*/
OpFormat(0, 1, OpArgR, OpArgK, iABC),   /*OP_GETTABLE*/
OpFormat(0, 1, OpArgK, OpArgU, iABx),   /*OP_SETGLOBAL*/
OpFormat(0, 1, OpArgU, OpArgN, iABC),   /*OP_SETUPVAL*/
OpFormat(0, 1, OpArgK, OpArgK, iABC),   /*OP_SETTABLE*/
OpFormat(0, 1, OpArgU, OpArgU, iABC),   /*OP_NEWTABLE*/
OpFormat(0, 1, OpArgR, OpArgK, iABC),   /*OP_SELF*/
OpFormat(0, 1, OpArgK, OpArgK, iABC),   /*OP_ADD*/
OpFormat(0, 1, OpArgK, OpArgK, iABC),   /*OP_SUB*/
OpFormat(0, 1, OpArgK, OpArgK, iABC),   /*OP_MUL*/
OpFormat(0, 1, OpArgK, OpArgK, iABC),   /*OP_DIV*/
OpFormat(0, 1, OpArgK, OpArgK, iABC),   /*OP_MOD*/
OpFormat(0, 1, OpArgK, OpArgK, iABC),   /*OP_POW*/
OpFormat(0, 1, OpArgR, OpArgN, iABC),   /*OP_UNM*/
OpFormat(0, 1, OpArgR, OpArgN, iABC),   /*OP_NOT*/
OpFormat(0, 1, OpArgR, OpArgN, iABC),   /*OP_LEN*/
OpFormat(0, 1, OpArgR, OpArgR, iABC),   /*OP_CONCAT*/
OpFormat(0, 0, OpArgR, OpArgN, iAsBx),  /*OP_JMP*/
OpFormat(1, 0, OpArgK, OpArgK, iABC),   /*OP_EQ*/
OpFormat(1, 0, OpArgK, OpArgK, iABC),   /*OP_LT*/
OpFormat(1, 0, OpArgK, OpArgK, iABC),   /*OP_LE*/
OpFormat(1, 0, OpArgN, OpArgU, iABC),   /*OP_TEST*/
OpFormat(1, 1, OpArgR, OpArgU, iABC),   /*OP_TESTSET*/
OpFormat(0, 1, OpArgU, OpArgU, iABC),   /*OP_CALL*/
OpFormat(0, 1, OpArgU, OpArgU, iABC),   /*OP_TAILCALL*/
OpFormat(0, 0, OpArgU, OpArgU, iABC),   /*OP_RETURN?*/
OpFormat(0, 1, OpArgR, OpArgN, iAsBx),  /*OP_FORLOOP*/
OpFormat(0, 1, OpArgR, OpArgN, iAsBx),  /*OP_FORPREP*/
OpFormat(0, 1, OpArgR, OpArgN, iAsBx),  /*OP_TFORLOOP*/
OpFormat(0, 0, OpArgU, OpArgU, iABC),   /*OP_SETLIST*/
OpFormat(0, 0, OpArgR, OpArgN, iABC),   /*OP_CLOSE*/
OpFormat(0, 1, OpArgU, OpArgN, iABx),   /*OP_CLOSURE*/
OpFormat(0, 1, OpArgU, OpArgN, iABC)    /*OP_VARARG*/

};




/*====================================================================
**
** Astro (Byte)Code Generator functions
**
**
=====================================================================*/


static int asC_code(FuncState *fs, Instruction i) {

    Proto *f = fs->f;
    //dischargePC_J()
    /*put new instruction in code array*/
    asM_growVector(fs->ls->S, f->code, fs->pc, f->size_code, INT_MAX, Instruction);
    f->code[fs->pc] = i;
    
    /*put line info into proto f*/
    asM_growVector(fs->ls->S, f->info_line, fs->pc, f->size_lineInfo, INT_MAX, int);
    f->info_line[fs->pc] = fs->ls->lastLine;
    
    return fs->pc++;
}


int asC_codeABC(FuncState *fs, as_OpCode o, int a, int b, int c) {

    as_assert(getOpMode(o) == iABC);
    as_assert(getModeArg_B(o) != OpArgN || b == 0);
    as_assert(getModeArg_C(o) != OpArgN || c == 0);
    as_assert(a <= MAXARG_A && b <= MAXARG_B && c <= MAXARG_C);

    return asC_code(fs, create_ABC(o, a, b, c));
}


int asC_codeABx(FuncState *fs, as_OpCode o, int a, unsigned int bx) {

    as_assert(getOpMode(o) == iABx || getOpMode(o) == iAsBx);
    as_assert(getModeArg_C(o) == OpArgN);
    as_assert(a <= MAXARG_A && bx <= MAXARG_Bx);

    return asC_code(fs, create_ABx(o, a, bx));
}
















